cfn_resource.py
cfn_resource_timeout-1.2.0.dist-info/DESCRIPTION.rst
cfn_resource_timeout-1.2.0.dist-info/METADATA
cfn_resource_timeout-1.2.0.dist-info/RECORD
cfn_resource_timeout-1.2.0.dist-info/WHEEL
cfn_resource_timeout-1.2.0.dist-info/metadata.json
cfn_resource_timeout-1.2.0.dist-info/top_level.txt
