Metadata-Version: 2.0
Name: cfn-resource-timeout
Version: 1.2.0
Summary: Wrapper decorators for building CloudFormation custom resources
Home-page: https://github.com/timeoutdigital/cfn-resource-timeout
Author: Adam Johnson
Author-email: adamjohnson@timeout.com
License: MIT
Keywords: cloudformation aws cloud custom resource amazon
Platform: UNKNOWN
Classifier: Development Status :: 5 - Production/Stable
Classifier: Intended Audience :: Developers
Classifier: License :: OSI Approved :: MIT License
Classifier: Programming Language :: Python :: 2
Classifier: Programming Language :: Python :: 2.7
Classifier: Programming Language :: Python :: 3
Classifier: Programming Language :: Python :: 3.6
Requires-Dist: requests
